Monei/__init__.py
Monei/api_client.py
Monei/api_response.py
Monei/configuration.py
Monei/exceptions.py
Monei/model_utils.py
Monei/monei_client.py
Monei/rest.py
Monei/api/__init__.py
Monei/api/apple_pay_domain_api.py
Monei/api/bizum_api.py
Monei/api/payment_methods_api.py
Monei/api/payments_api.py
Monei/api/subscriptions_api.py
Monei/apis/__init__.py
Monei/model/__init__.py
Monei/model/activate_subscription_request.py
Monei/model/address.py
Monei/model/api_exception.py
Monei/model/apple_pay_domain_register200_response.py
Monei/model/bad_request_error.py
Monei/model/bad_request_error_all_of.py
Monei/model/bizum_validate_phone200_response.py
Monei/model/cancel_payment_request.py
Monei/model/cancel_subscription_request.py
Monei/model/capture_payment_request.py
Monei/model/confirm_payment_request.py
Monei/model/confirm_payment_request_payment_method.py
Monei/model/confirm_payment_request_payment_method_card.py
Monei/model/create_payment_request.py
Monei/model/create_subscription_request.py
Monei/model/error_base.py
Monei/model/internal_server_error.py
Monei/model/internal_server_error_all_of.py
Monei/model/not_found_error.py
Monei/model/not_found_error_all_of.py
Monei/model/pause_subscription_request.py
Monei/model/payment.py
Monei/model/payment_billing_details.py
Monei/model/payment_cancellation_reason.py
Monei/model/payment_customer.py
Monei/model/payment_last_refund_reason.py
Monei/model/payment_message_channel.py
Monei/model/payment_message_language.py
Monei/model/payment_methods.py
Monei/model/payment_methods_metadata.py
Monei/model/payment_methods_metadata_alipay.py
Monei/model/payment_methods_metadata_apple_pay.py
Monei/model/payment_methods_metadata_bancontact.py
Monei/model/payment_methods_metadata_bizum.py
Monei/model/payment_methods_metadata_blik.py
Monei/model/payment_methods_metadata_card.py
Monei/model/payment_methods_metadata_click_to_pay.py
Monei/model/payment_methods_metadata_click_to_pay_discover.py
monei-2.4.0.dist-info/METADATA
monei-2.4.0.dist-info/WHEEL
monei-2.4.0.dist-info/licenses/LICENSE
monei-2.4.0.dist-info/RECORD
