Metadata-Version: 2.4
Name: Monei
Version: 2.4.0
Summary: MONEI PYTHON SDK
Project-URL: Repository, https://github.com/monei/monei-python-sdk
Author-email: MONEI <admin@monei.com>
License: MIT
License-File: LICENSE
Keywords: api,monei,monei pay,pay,payment gateway,payments,python,rest,sdk
Classifier: Development Status :: 5 - Production/Stable
Classifier: Intended Audience :: Developers
Classifier: License :: OSI Approved :: MIT License
Classifier: Operating System :: OS Independent
Classifier: Programming Language :: Python :: 3.8
Classifier: Programming Language :: Python :: 3.9
Classifier: Programming Language :: Python :: 3.10
Classifier: Programming Language :: Python :: 3.11
Classifier: Programming Language :: Python :: 3.12
Classifier: Topic :: Software Development :: Libraries :: Python Modules
Requires-Python: >=3.8
Requires-Dist: certifi
Requires-Dist: pydantic>=2
Requires-Dist: python-dateutil>=2.8.2
Requires-Dist: typing-extensions>=4.7.1
Requires-Dist: urllib3<3.0.0,>=1.25.3
